wurun.py
wurun-0.1.0.dist-info/licenses/LICENSE
wurun-0.1.0.dist-info/METADATA
wurun-0.1.0.dist-info/WHEEL
wurun-0.1.0.dist-info/top_level.txt
wurun-0.1.0.dist-info/RECORD
